{
  "series_id": "1034",
  "series_title": "Eşkıya Dünyaya Hükümdar Olmaz الموسم السادس",
  "episode_number": 18,
  "title": "الحلقة 18",
  "date_added": "الأربعاء 24 فبراير 2021 - 05:15 صباحا",
  "last_updated": "2026-01-13T03:48:44.444013Z",
  "servers": {
    "watch": [
      {
        "name": "أكوام",
        "type": "akwam",
        "url": "https://ak.sv/episode/25107/eşkıya-dünyaya-hükümdar-olmaz-الموسم-السادس/الحلقة-18",
        "quality": "720p",
        "source": "akwam"
      }
    ],
    "download": [
      {
        "name": "أكوام",
        "url": "https://ak.sv/episode/25107/eşkıya-dünyaya-hükümdar-olmaz-الموسم-السادس/الحلقة-18",
        "quality": "720p",
        "size": "",
        "source": "akwam"
      }
    ]
  }
}