{
  "series_id": "1038",
  "series_title": "Kuruluş Osman الموسم الثاني",
  "episode_number": 2,
  "title": "الحلقة 2",
  "date_added": "الخميس 15 أكتوبر 2020 - 02:42 صباحا",
  "last_updated": "2026-01-13T02:57:58.686090Z",
  "servers": {
    "watch": [
      {
        "name": "أكوام",
        "type": "akwam",
        "url": "https://ak.sv/episode/16797/kuruluş-osman-الموسم-الثاني/الحلقة-2",
        "quality": "720p",
        "source": "akwam"
      }
    ],
    "download": [
      {
        "name": "أكوام",
        "url": "https://ak.sv/episode/16797/kuruluş-osman-الموسم-الثاني/الحلقة-2",
        "quality": "720p",
        "size": "",
        "source": "akwam"
      }
    ]
  }
}