{
  "series_id": "1191",
  "series_title": "التفاح الحرام الموسم الثاني",
  "episode_number": 80,
  "title": "الحلقة 80",
  "date_added": "الإثنين 08 مارس 2021 - 12:07 صباحا",
  "last_updated": "2026-01-13T02:58:08.191393Z",
  "servers": {
    "watch": [
      {
        "name": "أكوام",
        "type": "akwam",
        "url": "https://ak.sv/episode/25970/التفاح-الحرام-الموسم-الثاني/الحلقة-80",
        "quality": "720p",
        "source": "akwam"
      }
    ],
    "download": [
      {
        "name": "أكوام",
        "url": "https://ak.sv/episode/25970/التفاح-الحرام-الموسم-الثاني/الحلقة-80",
        "quality": "720p",
        "size": "",
        "source": "akwam"
      }
    ]
  }
}