{
  "series_id": "1420",
  "series_title": "Seni Çok Bekledim",
  "episode_number": 11,
  "title": "الحلقة 11",
  "date_added": "السبت 10 ابريل 2021 - 10:20 صباحا",
  "last_updated": "2026-01-13T00:51:18.999749Z",
  "servers": {
    "watch": [
      {
        "name": "أكوام",
        "type": "akwam",
        "url": "https://ak.sv/episode/27720/seni-çok-bekledim/الحلقة-11",
        "quality": "720p",
        "source": "akwam"
      }
    ],
    "download": [
      {
        "name": "أكوام",
        "url": "https://ak.sv/episode/27720/seni-çok-bekledim/الحلقة-11",
        "quality": "720p",
        "size": "",
        "source": "akwam"
      }
    ]
  }
}