{
  "series_id": "1815",
  "series_title": "Ada Masali الموسم الاول",
  "episode_number": 8,
  "title": "الحلقة 8",
  "date_added": "الأربعاء 11 اغسطس 2021 - 04:39 صباحا",
  "last_updated": "2026-01-13T02:57:43.316814Z",
  "servers": {
    "watch": [
      {
        "name": "أكوام",
        "type": "akwam",
        "url": "https://ak.sv/episode/33839/ada-masali-الموسم-الاول/الحلقة-8",
        "quality": "720p",
        "source": "akwam"
      }
    ],
    "download": [
      {
        "name": "أكوام",
        "url": "https://ak.sv/episode/33839/ada-masali-الموسم-الاول/الحلقة-8",
        "quality": "720p",
        "size": "",
        "source": "akwam"
      }
    ]
  }
}