{
  "series_id": "1826",
  "series_title": "Ask mantik intikam الموسم الاول",
  "episode_number": 20,
  "title": "الحلقة 20",
  "date_added": "السبت 06 نوفمبر 2021 - 02:58 صباحا",
  "last_updated": "2026-01-13T02:57:27.948323Z",
  "servers": {
    "watch": [
      {
        "name": "أكوام",
        "type": "akwam",
        "url": "https://ak.sv/episode/39145/ask-mantik-intikam-الموسم-الاول/الحلقة-20",
        "quality": "720p",
        "source": "akwam"
      }
    ],
    "download": [
      {
        "name": "أكوام",
        "url": "https://ak.sv/episode/39145/ask-mantik-intikam-الموسم-الاول/الحلقة-20",
        "quality": "720p",
        "size": "",
        "source": "akwam"
      }
    ]
  }
}