{
  "series_id": "1905",
  "series_title": "عشق منطق انتقام الموسم الاول",
  "episode_number": 90,
  "title": "الحلقة 90",
  "date_added": "الإثنين 31 يناير 2022 - 01:52 صباحا",
  "last_updated": "2026-01-13T02:57:27.693980Z",
  "servers": {
    "watch": [
      {
        "name": "أكوام",
        "type": "akwam",
        "url": "https://ak.sv/episode/48499/عشق-منطق-انتقام-الموسم-الاول/الحلقة-90",
        "quality": "720p",
        "source": "akwam"
      }
    ],
    "download": [
      {
        "name": "أكوام",
        "url": "https://ak.sv/episode/48499/عشق-منطق-انتقام-الموسم-الاول/الحلقة-90",
        "quality": "720p",
        "size": "",
        "source": "akwam"
      }
    ]
  }
}