{
  "series_id": "1945",
  "series_title": "Benim Için Üzülme",
  "episode_number": 29,
  "title": "الحلقة 29",
  "date_added": "السبت 02 أكتوبر 2021 - 03:41 صباحا",
  "last_updated": "2026-01-13T00:50:40.308420Z",
  "servers": {
    "watch": [
      {
        "name": "أكوام",
        "type": "akwam",
        "url": "https://ak.sv/episode/36291/benim-için-üzülme/الحلقة-29",
        "quality": "720p",
        "source": "akwam"
      }
    ],
    "download": [
      {
        "name": "أكوام",
        "url": "https://ak.sv/episode/36291/benim-için-üzülme/الحلقة-29",
        "quality": "720p",
        "size": "",
        "source": "akwam"
      }
    ]
  }
}