{
  "series_id": "2017",
  "series_title": "Uzak Sehrin Masali الموسم الاول",
  "episode_number": 2,
  "title": "الحلقة 2",
  "date_added": "الإثنين 20 سبتمبر 2021 - 03:46 صباحا",
  "last_updated": "2026-01-13T06:17:42.326402Z",
  "servers": {
    "watch": [
      {
        "name": "أكوام",
        "type": "akwam",
        "url": "https://ak.sv/episode/35701/uzak-sehrin-masali-الموسم-الاول/الحلقة-2",
        "quality": "720p",
        "source": "akwam"
      }
    ],
    "download": [
      {
        "name": "أكوام",
        "url": "https://ak.sv/episode/35701/uzak-sehrin-masali-الموسم-الاول/الحلقة-2",
        "quality": "720p",
        "size": "",
        "source": "akwam"
      }
    ]
  }
}