{
  "series_id": "2021",
  "series_title": "زهرة الثالوث الموسم الاول",
  "episode_number": 119,
  "title": "الحلقة 119",
  "date_added": "الأحد 10 يوليو 2022 - 01:38 صباحا",
  "last_updated": "2026-01-13T06:17:06.530297Z",
  "servers": {
    "watch": [
      {
        "name": "أكوام",
        "type": "akwam",
        "url": "https://ak.sv/episode/62812/زهرة-الثالوث-الموسم-الاول/الحلقة-119",
        "quality": "720p",
        "source": "akwam"
      }
    ],
    "download": [
      {
        "name": "أكوام",
        "url": "https://ak.sv/episode/62812/زهرة-الثالوث-الموسم-الاول/الحلقة-119",
        "quality": "720p",
        "size": "",
        "source": "akwam"
      }
    ]
  }
}