{
  "series_id": "2024",
  "series_title": "Emanet الموسم الثاني",
  "episode_number": 106,
  "title": "الحلقة 106",
  "date_added": "الأربعاء 09 فبراير 2022 - 03:29 صباحا",
  "last_updated": "2026-01-14T08:41:42.765551Z",
  "servers": {
    "watch": [
      {
        "name": "أكوام",
        "type": "akwam",
        "url": "https://ak.sv/episode/49441/emanet-الموسم-الثاني/الحلقة-106",
        "quality": "720p",
        "source": "akwam"
      }
    ],
    "download": [
      {
        "name": "أكوام",
        "url": "https://ak.sv/episode/49441/emanet-الموسم-الثاني/الحلقة-106",
        "quality": "720p",
        "size": "",
        "source": "akwam"
      }
    ]
  }
}