{
  "series_id": "2124",
  "series_title": "Şahane Damat",
  "episode_number": 5,
  "title": "الحلقة 5",
  "date_added": "الأحد 10 أكتوبر 2021 - 04:20 صباحا",
  "last_updated": "2026-01-13T00:50:54.492172Z",
  "servers": {
    "watch": [
      {
        "name": "أكوام",
        "type": "akwam",
        "url": "https://ak.sv/episode/36749/şahane-damat/الحلقة-5",
        "quality": "720p",
        "source": "akwam"
      }
    ],
    "download": [
      {
        "name": "أكوام",
        "url": "https://ak.sv/episode/36749/şahane-damat/الحلقة-5",
        "quality": "720p",
        "size": "",
        "source": "akwam"
      }
    ]
  }
}