{
  "series_id": "2130",
  "series_title": "Çukur الجزء الثالث",
  "episode_number": 6,
  "title": "الحلقة 6",
  "date_added": "الثلاثاء 12 أكتوبر 2021 - 04:36 صباحا",
  "last_updated": "2026-01-13T00:50:52.743399Z",
  "servers": {
    "watch": [
      {
        "name": "أكوام",
        "type": "akwam",
        "url": "https://ak.sv/episode/37054/çukur-الجزء-الثالث/الحلقة-6",
        "quality": "720p",
        "source": "akwam"
      }
    ],
    "download": [
      {
        "name": "أكوام",
        "url": "https://ak.sv/episode/37054/çukur-الجزء-الثالث/الحلقة-6",
        "quality": "720p",
        "size": "",
        "source": "akwam"
      }
    ]
  }
}