{
  "series_id": "2150",
  "series_title": "الحفرة الجزء الثاني",
  "episode_number": 45,
  "title": "الحلقة 45",
  "date_added": "الثلاثاء 19 أكتوبر 2021 - 04:28 مساءاً",
  "last_updated": "2026-01-13T03:48:32.044447Z",
  "servers": {
    "watch": [
      {
        "name": "أكوام",
        "type": "akwam",
        "url": "https://ak.sv/episode/38006/الحفرة-الجزء-الثاني/الحلقة-45",
        "quality": "720p",
        "source": "akwam"
      }
    ],
    "download": [
      {
        "name": "أكوام",
        "url": "https://ak.sv/episode/38006/الحفرة-الجزء-الثاني/الحلقة-45",
        "quality": "720p",
        "size": "",
        "source": "akwam"
      }
    ]
  }
}