{
  "series_id": "2235",
  "series_title": "ثلاثة قروش الموسم الاول",
  "episode_number": 81,
  "title": "الحلقة 81",
  "date_added": "الخميس 26 مايو 2022 - 03:35 صباحا",
  "last_updated": "2026-01-14T08:41:57.308636Z",
  "servers": {
    "watch": [
      {
        "name": "أكوام",
        "type": "akwam",
        "url": "https://ak.sv/episode/60554/ثلاثة-قروش-الموسم-الاول/الحلقة-81",
        "quality": "720p",
        "source": "akwam"
      }
    ],
    "download": [
      {
        "name": "أكوام",
        "url": "https://ak.sv/episode/60554/ثلاثة-قروش-الموسم-الاول/الحلقة-81",
        "quality": "720p",
        "size": "",
        "source": "akwam"
      }
    ]
  }
}