{
  "series_id": "2246",
  "series_title": "Aziz الموسم الأول",
  "episode_number": 17,
  "title": "الحلقة 17",
  "date_added": "السبت 12 مارس 2022 - 03:37 صباحا",
  "last_updated": "2026-01-13T00:50:16.409854Z",
  "servers": {
    "watch": [
      {
        "name": "أكوام",
        "type": "akwam",
        "url": "https://ak.sv/episode/53573/aziz-الموسم-الأول/الحلقة-17",
        "quality": "720p",
        "source": "akwam"
      }
    ],
    "download": [
      {
        "name": "أكوام",
        "url": "https://ak.sv/episode/53573/aziz-الموسم-الأول/الحلقة-17",
        "quality": "720p",
        "size": "",
        "source": "akwam"
      }
    ]
  }
}