{
  "series_id": "2579",
  "series_title": "جسور والجميلة الموسم الاول",
  "episode_number": 47,
  "title": "الحلقة 47",
  "date_added": "الأربعاء 12 يناير 2022 - 04:50 مساءاً",
  "last_updated": "2026-01-13T02:57:32.189013Z",
  "servers": {
    "watch": [
      {
        "name": "أكوام",
        "type": "akwam",
        "url": "https://ak.sv/episode/45892/جسور-والجميلة-الموسم-الاول/الحلقة-47",
        "quality": "720p",
        "source": "akwam"
      }
    ],
    "download": [
      {
        "name": "أكوام",
        "url": "https://ak.sv/episode/45892/جسور-والجميلة-الموسم-الاول/الحلقة-47",
        "quality": "720p",
        "size": "",
        "source": "akwam"
      }
    ]
  }
}