{
  "series_id": "2600",
  "series_title": "ظلال الماضي الموسم الاول",
  "episode_number": 10,
  "title": "الحلقة 10",
  "date_added": "الخميس 13 يناير 2022 - 09:35 مساءاً",
  "last_updated": "2026-01-13T02:57:38.997691Z",
  "servers": {
    "watch": [
      {
        "name": "أكوام",
        "type": "akwam",
        "url": "https://ak.sv/episode/46180/ظلال-الماضي-الموسم-الاول/الحلقة-10",
        "quality": "720p",
        "source": "akwam"
      }
    ],
    "download": [
      {
        "name": "أكوام",
        "url": "https://ak.sv/episode/46180/ظلال-الماضي-الموسم-الاول/الحلقة-10",
        "quality": "720p",
        "size": "",
        "source": "akwam"
      }
    ]
  }
}