{
  "series_id": "2650",
  "series_title": "حريم السلطان الموسم الثالث",
  "episode_number": 99,
  "title": "الحلقة 99",
  "date_added": "الإثنين 24 يناير 2022 - 03:31 صباحا",
  "last_updated": "2026-01-13T03:48:21.854817Z",
  "servers": {
    "watch": [
      {
        "name": "أكوام",
        "type": "akwam",
        "url": "https://ak.sv/episode/47926/حريم-السلطان-الموسم-الثالث/الحلقة-99",
        "quality": "720p",
        "source": "akwam"
      }
    ],
    "download": [
      {
        "name": "أكوام",
        "url": "https://ak.sv/episode/47926/حريم-السلطان-الموسم-الثالث/الحلقة-99",
        "quality": "720p",
        "size": "",
        "source": "akwam"
      }
    ]
  }
}