{
  "series_id": "2669",
  "series_title": "حريم السلطان الموسم الرابع",
  "episode_number": 83,
  "title": "الحلقة 83",
  "date_added": "الأربعاء 26 يناير 2022 - 11:05 صباحا",
  "last_updated": "2026-01-13T00:50:36.660755Z",
  "servers": {
    "watch": [
      {
        "name": "أكوام",
        "type": "akwam",
        "url": "https://ak.sv/episode/48167/حريم-السلطان-الموسم-الرابع/الحلقة-83",
        "quality": "720p",
        "source": "akwam"
      }
    ],
    "download": [
      {
        "name": "أكوام",
        "url": "https://ak.sv/episode/48167/حريم-السلطان-الموسم-الرابع/الحلقة-83",
        "quality": "720p",
        "size": "",
        "source": "akwam"
      }
    ]
  }
}