{
  "series_id": "2804",
  "series_title": "Üç Kiz Kardes الموسم الاول",
  "episode_number": 12,
  "title": "الحلقة 12",
  "date_added": "الأربعاء 18 مايو 2022 - 03:58 صباحا",
  "last_updated": "2026-01-13T06:17:10.486544Z",
  "servers": {
    "watch": [
      {
        "name": "أكوام",
        "type": "akwam",
        "url": "https://ak.sv/episode/60080/üç-kiz-kardes-الموسم-الاول/الحلقة-12",
        "quality": "720p",
        "source": "akwam"
      }
    ],
    "download": [
      {
        "name": "أكوام",
        "url": "https://ak.sv/episode/60080/üç-kiz-kardes-الموسم-الاول/الحلقة-12",
        "quality": "720p",
        "size": "",
        "source": "akwam"
      }
    ]
  }
}