{
  "series_id": "2848",
  "series_title": "الحفرة الجزء الرابع",
  "episode_number": 40,
  "title": "الحلقة 40",
  "date_added": "الأحد 06 مارس 2022 - 04:26 مساءاً",
  "last_updated": "2026-01-13T03:48:10.196044Z",
  "servers": {
    "watch": [
      {
        "name": "أكوام",
        "type": "akwam",
        "url": "https://ak.sv/episode/52690/الحفرة-الجزء-الرابع/الحلقة-40",
        "quality": "720p",
        "source": "akwam"
      }
    ],
    "download": [
      {
        "name": "أكوام",
        "url": "https://ak.sv/episode/52690/الحفرة-الجزء-الرابع/الحلقة-40",
        "quality": "720p",
        "size": "",
        "source": "akwam"
      }
    ]
  }
}