{
  "series_id": "3025",
  "series_title": "المدينة المفقودة الموسم الاول",
  "episode_number": 25,
  "title": "الحلقة 25",
  "date_added": "الثلاثاء 29 مارس 2022 - 02:18 مساءاً",
  "last_updated": "2026-01-14T08:42:10.578992Z",
  "servers": {
    "watch": [
      {
        "name": "أكوام",
        "type": "akwam",
        "url": "https://ak.sv/episode/55867/المدينة-المفقودة-الموسم-الاول/الحلقة-25",
        "quality": "720p",
        "source": "akwam"
      }
    ],
    "download": [
      {
        "name": "أكوام",
        "url": "https://ak.sv/episode/55867/المدينة-المفقودة-الموسم-الاول/الحلقة-25",
        "quality": "720p",
        "size": "",
        "source": "akwam"
      }
    ]
  }
}