{
  "series_id": "3136",
  "series_title": "لعبة قدري الموسم الاول",
  "episode_number": 11,
  "title": "الحلقة 11",
  "date_added": "الأحد 15 مايو 2022 - 07:30 مساءاً",
  "last_updated": "2026-01-13T03:47:49.823584Z",
  "servers": {
    "watch": [
      {
        "name": "أكوام",
        "type": "akwam",
        "url": "https://ak.sv/episode/59936/لعبة-قدري-الموسم-الاول/الحلقة-11",
        "quality": "720p",
        "source": "akwam"
      }
    ],
    "download": [
      {
        "name": "أكوام",
        "url": "https://ak.sv/episode/59936/لعبة-قدري-الموسم-الاول/الحلقة-11",
        "quality": "720p",
        "size": "",
        "source": "akwam"
      }
    ]
  }
}