{
  "series_id": "3137",
  "series_title": "اللهيب الموسم الاول",
  "episode_number": 48,
  "title": "الحلقة 48",
  "date_added": "الثلاثاء 19 يوليو 2022 - 04:58 صباحا",
  "last_updated": "2026-01-13T03:47:55.830856Z",
  "servers": {
    "watch": [
      {
        "name": "أكوام",
        "type": "akwam",
        "url": "https://ak.sv/episode/63255/اللهيب-الموسم-الاول/الحلقة-48",
        "quality": "720p",
        "source": "akwam"
      }
    ],
    "download": [
      {
        "name": "أكوام",
        "url": "https://ak.sv/episode/63255/اللهيب-الموسم-الاول/الحلقة-48",
        "quality": "720p",
        "size": "",
        "source": "akwam"
      }
    ]
  }
}