{
  "series_id": "3137",
  "series_title": "اللهيب الموسم الاول",
  "episode_number": 10,
  "title": "الحلقة 10",
  "date_added": "الأحد 29 مايو 2022 - 04:02 صباحا",
  "last_updated": "2026-01-13T00:50:03.974675Z",
  "servers": {
    "watch": [
      {
        "name": "أكوام",
        "type": "akwam",
        "url": "https://ak.sv/episode/60674/اللهيب-الموسم-الاول/الحلقة-10",
        "quality": "720p",
        "source": "akwam"
      }
    ],
    "download": [
      {
        "name": "أكوام",
        "url": "https://ak.sv/episode/60674/اللهيب-الموسم-الاول/الحلقة-10",
        "quality": "720p",
        "size": "",
        "source": "akwam"
      }
    ]
  }
}