{
  "series_id": "3137",
  "series_title": "اللهيب الموسم الاول",
  "episode_number": 52,
  "title": "الحلقة 52",
  "date_added": "الإثنين 25 يوليو 2022 - 04:23 صباحا",
  "last_updated": "2026-01-14T08:41:31.845855Z",
  "servers": {
    "watch": [
      {
        "name": "أكوام",
        "type": "akwam",
        "url": "https://ak.sv/episode/63608/اللهيب-الموسم-الاول/الحلقة-52",
        "quality": "720p",
        "source": "akwam"
      }
    ],
    "download": [
      {
        "name": "أكوام",
        "url": "https://ak.sv/episode/63608/اللهيب-الموسم-الاول/الحلقة-52",
        "quality": "720p",
        "size": "",
        "source": "akwam"
      }
    ]
  }
}