{
  "series_id": "3151",
  "series_title": "الغرفة الحمراء الموسم الثاني",
  "episode_number": 65,
  "title": "الحلقة 65",
  "date_added": "الثلاثاء 26 يوليو 2022 - 02:03 صباحا",
  "last_updated": "2026-01-14T08:41:37.044566Z",
  "servers": {
    "watch": [
      {
        "name": "أكوام",
        "type": "akwam",
        "url": "https://ak.sv/episode/63631/الغرفة-الحمراء-الموسم-الثاني/الحلقة-65",
        "quality": "720p",
        "source": "akwam"
      }
    ],
    "download": [
      {
        "name": "أكوام",
        "url": "https://ak.sv/episode/63631/الغرفة-الحمراء-الموسم-الثاني/الحلقة-65",
        "quality": "720p",
        "size": "",
        "source": "akwam"
      }
    ]
  }
}