{
  "series_id": "3221",
  "series_title": "اخوتي الموسم الثاني",
  "episode_number": 102,
  "title": "الحلقة 102",
  "date_added": "الإثنين 07 نوفمبر 2022 - 02:24 صباحا",
  "last_updated": "2026-01-13T00:49:56.508591Z",
  "servers": {
    "watch": [
      {
        "name": "أكوام",
        "type": "akwam",
        "url": "https://ak.sv/episode/68726/اخوتي-الموسم-الثاني/الحلقة-102",
        "quality": "720p",
        "source": "akwam"
      }
    ],
    "download": [
      {
        "name": "أكوام",
        "url": "https://ak.sv/episode/68726/اخوتي-الموسم-الثاني/الحلقة-102",
        "quality": "720p",
        "size": "",
        "source": "akwam"
      }
    ]
  }
}