{
  "series_id": "3277",
  "series_title": "Duy Beni الموسم الاول",
  "episode_number": 1,
  "title": "الحلقة 1",
  "date_added": "الجمعة 08 يوليو 2022 - 02:21 صباحا",
  "last_updated": "2026-01-13T02:57:07.560271Z",
  "servers": {
    "watch": [
      {
        "name": "أكوام",
        "type": "akwam",
        "url": "https://ak.sv/episode/62772/duy-beni-الموسم-الاول/الحلقة-1",
        "quality": "720p",
        "source": "akwam"
      }
    ],
    "download": [
      {
        "name": "أكوام",
        "url": "https://ak.sv/episode/62772/duy-beni-الموسم-الاول/الحلقة-1",
        "quality": "720p",
        "size": "",
        "source": "akwam"
      }
    ]
  }
}