{
  "series_id": "3296",
  "series_title": "Mezarlik الموسم الاول",
  "episode_number": 2,
  "title": "الحلقة 2",
  "date_added": "الأحد 17 يوليو 2022 - 05:20 صباحا",
  "last_updated": "2026-01-13T03:47:59.271129Z",
  "servers": {
    "watch": [
      {
        "name": "أكوام",
        "type": "akwam",
        "url": "https://ak.sv/episode/63157/mezarlik-الموسم-الاول/الحلقة-2",
        "quality": "720p",
        "source": "akwam"
      }
    ],
    "download": [
      {
        "name": "أكوام",
        "url": "https://ak.sv/episode/63157/mezarlik-الموسم-الاول/الحلقة-2",
        "quality": "720p",
        "size": "",
        "source": "akwam"
      }
    ]
  }
}