{
  "series_id": "3507",
  "series_title": "Camdaki Kiz الموسم الثالث",
  "episode_number": 27,
  "title": "الحلقة 27",
  "date_added": "الجمعة 14 ابريل 2023 - 03:35 مساءاً",
  "last_updated": "2026-01-13T03:47:33.356394Z",
  "servers": {
    "watch": [
      {
        "name": "أكوام",
        "type": "akwam",
        "url": "https://ak.sv/episode/76326/camdaki-kiz-الموسم-الثالث/الحلقة-27",
        "quality": "720p",
        "source": "akwam"
      }
    ],
    "download": [
      {
        "name": "أكوام",
        "url": "https://ak.sv/episode/76326/camdaki-kiz-الموسم-الثالث/الحلقة-27",
        "quality": "720p",
        "size": "",
        "source": "akwam"
      }
    ]
  }
}