{
  "series_id": "3570",
  "series_title": "Yali Çapkini الموسم الاول",
  "episode_number": 7,
  "title": "الحلقة 7",
  "date_added": "السبت 05 نوفمبر 2022 - 03:06 صباحا",
  "last_updated": "2026-01-14T08:40:45.772876Z",
  "servers": {
    "watch": [
      {
        "name": "أكوام",
        "type": "akwam",
        "url": "https://ak.sv/episode/68662/yali-çapkini-الموسم-الاول/الحلقة-7",
        "quality": "720p",
        "source": "akwam"
      }
    ],
    "download": [
      {
        "name": "أكوام",
        "url": "https://ak.sv/episode/68662/yali-çapkini-الموسم-الاول/الحلقة-7",
        "quality": "720p",
        "size": "",
        "source": "akwam"
      }
    ]
  }
}