{
  "series_id": "3666",
  "series_title": "لعبة الحياة الموسم الاول",
  "episode_number": 32,
  "title": "الحلقة 32",
  "date_added": "الجمعة 02 ديسمبر 2022 - 03:19 صباحا",
  "last_updated": "2026-01-13T03:47:50.085457Z",
  "servers": {
    "watch": [
      {
        "name": "أكوام",
        "type": "akwam",
        "url": "https://ak.sv/episode/69889/لعبة-الحياة-الموسم-الاول/الحلقة-32",
        "quality": "720p",
        "source": "akwam"
      }
    ],
    "download": [
      {
        "name": "أكوام",
        "url": "https://ak.sv/episode/69889/لعبة-الحياة-الموسم-الاول/الحلقة-32",
        "quality": "720p",
        "size": "",
        "source": "akwam"
      }
    ]
  }
}