{
  "series_id": "3689",
  "series_title": "فريد الموسم الاول",
  "episode_number": 55,
  "title": "الحلقة 55",
  "date_added": "الإثنين 05 ديسمبر 2022 - 01:22 صباحا",
  "last_updated": "2026-01-13T03:47:35.433715Z",
  "servers": {
    "watch": [
      {
        "name": "أكوام",
        "type": "akwam",
        "url": "https://ak.sv/episode/70041/فريد-الموسم-الاول/الحلقة-55",
        "quality": "720p",
        "source": "akwam"
      }
    ],
    "download": [
      {
        "name": "أكوام",
        "url": "https://ak.sv/episode/70041/فريد-الموسم-الاول/الحلقة-55",
        "quality": "720p",
        "size": "",
        "source": "akwam"
      }
    ]
  }
}