{
  "series_id": "3907",
  "series_title": "Ates Kuslari الموسم الاول",
  "episode_number": 12,
  "title": "الحلقة 12",
  "date_added": "السبت 15 ابريل 2023 - 01:40 مساءاً",
  "last_updated": "2026-01-14T08:40:36.921418Z",
  "servers": {
    "watch": [
      {
        "name": "أكوام",
        "type": "akwam",
        "url": "https://ak.sv/episode/76395/ates-kuslari-الموسم-الاول/الحلقة-12",
        "quality": "720p",
        "source": "akwam"
      }
    ],
    "download": [
      {
        "name": "أكوام",
        "url": "https://ak.sv/episode/76395/ates-kuslari-الموسم-الاول/الحلقة-12",
        "quality": "720p",
        "size": "",
        "source": "akwam"
      }
    ]
  }
}