{
  "series_id": "4271",
  "series_title": "الطفل الموسم الاول",
  "episode_number": 19,
  "title": "الحلقة 19",
  "date_added": "السبت 15 يوليو 2023 - 09:18 مساءاً",
  "last_updated": "2026-01-13T02:56:37.892873Z",
  "servers": {
    "watch": [
      {
        "name": "أكوام",
        "type": "akwam",
        "url": "https://ak.sv/episode/79173/الطفل-الموسم-الاول/الحلقة-19",
        "quality": "720p",
        "source": "akwam"
      }
    ],
    "download": [
      {
        "name": "أكوام",
        "url": "https://ak.sv/episode/79173/الطفل-الموسم-الاول/الحلقة-19",
        "quality": "720p",
        "size": "",
        "source": "akwam"
      }
    ]
  }
}