{
  "series_id": "4271",
  "series_title": "الطفل الموسم الاول",
  "episode_number": 32,
  "title": "الحلقة 32",
  "date_added": "الجمعة 11 اغسطس 2023 - 02:45 صباحا",
  "last_updated": "2026-01-14T08:40:10.508417Z",
  "servers": {
    "watch": [
      {
        "name": "أكوام",
        "type": "akwam",
        "url": "https://ak.sv/episode/79718/الطفل-الموسم-الاول/الحلقة-32",
        "quality": "720p",
        "source": "akwam"
      }
    ],
    "download": [
      {
        "name": "أكوام",
        "url": "https://ak.sv/episode/79718/الطفل-الموسم-الاول/الحلقة-32",
        "quality": "720p",
        "size": "",
        "source": "akwam"
      }
    ]
  }
}