{
  "series_id": "4325",
  "series_title": "Ya Çok Seversen الموسم الاول",
  "episode_number": 9,
  "title": "الحلقة 9",
  "date_added": "الأحد 03 سبتمبر 2023 - 04:23 صباحا",
  "last_updated": "2026-01-13T02:56:37.403934Z",
  "servers": {
    "watch": [
      {
        "name": "أكوام",
        "type": "akwam",
        "url": "https://ak.sv/episode/80098/ya-çok-seversen-الموسم-الاول/الحلقة-9",
        "quality": "720p",
        "source": "akwam"
      }
    ],
    "download": [
      {
        "name": "أكوام",
        "url": "https://ak.sv/episode/80098/ya-çok-seversen-الموسم-الاول/الحلقة-9",
        "quality": "720p",
        "size": "",
        "source": "akwam"
      }
    ]
  }
}