{
  "series_id": "4397",
  "series_title": "أمي الموسم الاول",
  "episode_number": 75,
  "title": "الحلقة 75",
  "date_added": "الإثنين 25 سبتمبر 2023 - 07:19 مساءاً",
  "last_updated": "2026-01-13T02:56:36.199628Z",
  "servers": {
    "watch": [
      {
        "name": "أكوام",
        "type": "akwam",
        "url": "https://ak.sv/episode/80828/أمي-الموسم-الاول/الحلقة-75",
        "quality": "720p",
        "source": "akwam"
      }
    ],
    "download": [
      {
        "name": "أكوام",
        "url": "https://ak.sv/episode/80828/أمي-الموسم-الاول/الحلقة-75",
        "quality": "720p",
        "size": "",
        "source": "akwam"
      }
    ]
  }
}