{
  "series_id": "4443",
  "series_title": "Kizilcik Serbeti الموسم الثاني",
  "episode_number": 12,
  "title": "الحلقة 12",
  "date_added": "السبت 02 ديسمبر 2023 - 08:40 مساءاً",
  "last_updated": "2026-01-13T03:47:14.526532Z",
  "servers": {
    "watch": [
      {
        "name": "أكوام",
        "type": "akwam",
        "url": "https://ak.sv/episode/82722/kizilcik-serbeti-الموسم-الثاني/الحلقة-12",
        "quality": "720p",
        "source": "akwam"
      }
    ],
    "download": [
      {
        "name": "أكوام",
        "url": "https://ak.sv/episode/82722/kizilcik-serbeti-الموسم-الثاني/الحلقة-12",
        "quality": "720p",
        "size": "",
        "source": "akwam"
      }
    ]
  }
}