{
  "series_id": "4517",
  "series_title": "الصيف الاخير الموسم الاول",
  "episode_number": 46,
  "title": "الحلقة 46",
  "date_added": "الأربعاء 29 نوفمبر 2023 - 08:35 مساءاً",
  "last_updated": "2026-01-13T03:47:15.512409Z",
  "servers": {
    "watch": [
      {
        "name": "أكوام",
        "type": "akwam",
        "url": "https://ak.sv/episode/82625/الصيف-الاخير-الموسم-الاول/الحلقة-46",
        "quality": "720p",
        "source": "akwam"
      }
    ],
    "download": [
      {
        "name": "أكوام",
        "url": "https://ak.sv/episode/82625/الصيف-الاخير-الموسم-الاول/الحلقة-46",
        "quality": "720p",
        "size": "",
        "source": "akwam"
      }
    ]
  }
}