{
  "series_id": "4566",
  "series_title": "المتوحش الموسم الاول",
  "episode_number": 50,
  "title": "الحلقة 50",
  "date_added": "الأربعاء 29 نوفمبر 2023 - 07:33 مساءاً",
  "last_updated": "2026-01-13T06:16:08.592406Z",
  "servers": {
    "watch": [
      {
        "name": "أكوام",
        "type": "akwam",
        "url": "https://ak.sv/episode/82600/المتوحش-الموسم-الاول/الحلقة-50",
        "quality": "720p",
        "source": "akwam"
      }
    ],
    "download": [
      {
        "name": "أكوام",
        "url": "https://ak.sv/episode/82600/المتوحش-الموسم-الاول/الحلقة-50",
        "quality": "720p",
        "size": "",
        "source": "akwam"
      }
    ]
  }
}