{
  "series_id": "4574",
  "series_title": "Teşkilat الموسم الرابع",
  "episode_number": 5,
  "title": "الحلقة 5",
  "date_added": "الإثنين 20 نوفمبر 2023 - 08:26 مساءاً",
  "last_updated": "2026-01-13T06:16:08.175562Z",
  "servers": {
    "watch": [
      {
        "name": "أكوام",
        "type": "akwam",
        "url": "https://ak.sv/episode/82307/teşkilat-الموسم-الرابع/الحلقة-5",
        "quality": "720p",
        "source": "akwam"
      }
    ],
    "download": [
      {
        "name": "أكوام",
        "url": "https://ak.sv/episode/82307/teşkilat-الموسم-الرابع/الحلقة-5",
        "quality": "720p",
        "size": "",
        "source": "akwam"
      }
    ]
  }
}