{
  "series_id": "5010",
  "series_title": "فندق الاحلام مدبلج",
  "episode_number": 2,
  "title": "الحلقة 2",
  "date_added": "الإثنين 21 يوليو 2025 - 02:24 مساءاً",
  "last_updated": "2026-01-13T03:47:05.951987Z",
  "servers": {
    "watch": [
      {
        "name": "أكوام",
        "type": "akwam",
        "url": "https://ak.sv/episode/88524/فندق-الاحلام-مدبلج/الحلقة-2",
        "quality": "720p",
        "source": "akwam"
      }
    ],
    "download": [
      {
        "name": "أكوام",
        "url": "https://ak.sv/episode/88524/فندق-الاحلام-مدبلج/الحلقة-2",
        "quality": "720p",
        "size": "",
        "source": "akwam"
      }
    ]
  }
}