{
  "series_id": "5037",
  "series_title": "ما تراه ليس كما يبدو",
  "episode_number": 5,
  "title": "الحلقة 5",
  "date_added": "الأربعاء 13 اغسطس 2025 - 09:18 مساءاً",
  "last_updated": "2026-01-12T20:44:43.214052Z",
  "servers": {
    "watch": [
      {
        "name": "أكوام",
        "type": "akwam",
        "url": "https://ak.sv/episode/88898/ما-تراه-ليس-كما-يبدو/الحلقة-5",
        "quality": "720p",
        "source": "akwam"
      }
    ],
    "download": [
      {
        "name": "أكوام",
        "url": "https://ak.sv/episode/88898/ما-تراه-ليس-كما-يبدو/الحلقة-5",
        "quality": "720p",
        "size": "",
        "source": "akwam"
      }
    ]
  }
}