{
  "series_id": "5044",
  "series_title": "الزوجة الاخرى مدبلج",
  "episode_number": 21,
  "title": "الحلقة 21",
  "date_added": "السبت 27 سبتمبر 2025 - 06:27 مساءاً",
  "last_updated": "2026-01-13T02:56:16.717592Z",
  "servers": {
    "watch": [
      {
        "name": "أكوام",
        "type": "akwam",
        "url": "https://ak.sv/episode/89564/الزوجة-الاخرى-مدبلج/الحلقة-21",
        "quality": "720p",
        "source": "akwam"
      }
    ],
    "download": [
      {
        "name": "أكوام",
        "url": "https://ak.sv/episode/89564/الزوجة-الاخرى-مدبلج/الحلقة-21",
        "quality": "720p",
        "size": "",
        "source": "akwam"
      }
    ]
  }
}