{
  "series_id": "5053",
  "series_title": "The Terminal List: Dark Wolf مدبلج",
  "episode_number": 4,
  "title": "الحلقة 4",
  "date_added": "الثلاثاء 23 سبتمبر 2025 - 09:38 مساءاً",
  "last_updated": "2026-01-12T20:44:41.074602Z",
  "servers": {
    "watch": [
      {
        "name": "أكوام",
        "type": "akwam",
        "url": "https://ak.sv/episode/89492/the-terminal-list-dark-wolf-مدبلج/الحلقة-4",
        "quality": "720p",
        "source": "akwam"
      }
    ],
    "download": [
      {
        "name": "أكوام",
        "url": "https://ak.sv/episode/89492/the-terminal-list-dark-wolf-مدبلج/الحلقة-4",
        "quality": "720p",
        "size": "",
        "source": "akwam"
      }
    ]
  }
}