{
  "series_id": "5077",
  "series_title": "وأزهر الحب",
  "episode_number": 18,
  "title": "الحلقة 18",
  "date_added": "الثلاثاء 07 أكتوبر 2025 - 11:54 مساءاً",
  "last_updated": "2026-01-12T20:43:43.381556Z",
  "servers": {
    "watch": [
      {
        "name": "أكوام",
        "type": "akwam",
        "url": "https://ak.sv/episode/89758/وأزهر-الحب/الحلقة-18",
        "quality": "720p",
        "source": "akwam"
      }
    ],
    "download": [
      {
        "name": "أكوام",
        "url": "https://ak.sv/episode/89758/وأزهر-الحب/الحلقة-18",
        "quality": "720p",
        "size": "",
        "source": "akwam"
      }
    ]
  }
}