{
  "series_id": "5085",
  "series_title": "المدينة البعيدة الموسم الثاني مدبلج",
  "episode_number": 86,
  "title": "الحلقة 86",
  "date_added": "الأربعاء 21 يناير 2026 - 10:06 مساءاً",
  "last_updated": "2026-01-27T12:21:28.180136Z",
  "servers": {
    "watch": [
      {
        "name": "أكوام",
        "type": "akwam",
        "url": "https://ak.sv/episode/92726/المدينة-البعيدة-الموسم-الثاني-مدبلج/الحلقة-86",
        "quality": "720p",
        "source": "akwam"
      }
    ],
    "download": [
      {
        "name": "أكوام",
        "url": "https://ak.sv/episode/92726/المدينة-البعيدة-الموسم-الثاني-مدبلج/الحلقة-86",
        "quality": "720p",
        "size": "",
        "source": "akwam"
      }
    ]
  }
}