{
  "series_id": "5085",
  "series_title": "المدينة البعيدة الموسم الثاني مدبلج",
  "episode_number": 10,
  "title": "الحلقة 10",
  "date_added": "السبت 27 سبتمبر 2025 - 08:43 مساءاً",
  "last_updated": "2026-01-13T06:15:55.997693Z",
  "servers": {
    "watch": [
      {
        "name": "أكوام",
        "type": "akwam",
        "url": "https://ak.sv/episode/89571/المدينة-البعيدة-الموسم-الثاني-مدبلج/الحلقة-10",
        "quality": "720p",
        "source": "akwam"
      }
    ],
    "download": [
      {
        "name": "أكوام",
        "url": "https://ak.sv/episode/89571/المدينة-البعيدة-الموسم-الثاني-مدبلج/الحلقة-10",
        "quality": "720p",
        "size": "",
        "source": "akwam"
      }
    ]
  }
}