{
  "series_id": "5087",
  "series_title": "حلم اشرف الموسم الثاني مترجم",
  "episode_number": 38,
  "title": "الحلقة 38",
  "date_added": "الجمعة 27 مارس 2026 - 01:07 صباحا",
  "last_updated": "2026-03-27T06:57:11.699786Z",
  "servers": {
    "watch": [
      {
        "name": "أكوام",
        "type": "akwam",
        "url": "https://ak.sv/episode/98521/حلم-اشرف-الموسم-الثاني-مترجم/الحلقة-38",
        "quality": "720p",
        "source": "akwam"
      }
    ],
    "download": [
      {
        "name": "أكوام",
        "url": "https://ak.sv/episode/98521/حلم-اشرف-الموسم-الثاني-مترجم/الحلقة-38",
        "quality": "720p",
        "size": "",
        "source": "akwam"
      }
    ]
  }
}