{
  "series_id": "5089",
  "series_title": "اطفال الجنة مترجم",
  "episode_number": 24,
  "title": "الحلقة 24",
  "date_added": "الخميس 26 مارس 2026 - 09:40 مساءاً",
  "last_updated": "2026-03-27T06:56:36.234235Z",
  "servers": {
    "watch": [
      {
        "name": "أكوام",
        "type": "akwam",
        "url": "https://ak.sv/episode/98474/اطفال-الجنة-مترجم/الحلقة-24",
        "quality": "720p",
        "source": "akwam"
      }
    ],
    "download": [
      {
        "name": "أكوام",
        "url": "https://ak.sv/episode/98474/اطفال-الجنة-مترجم/الحلقة-24",
        "quality": "720p",
        "size": "",
        "source": "akwam"
      }
    ]
  }
}