{
  "series_id": "5089",
  "series_title": "اطفال الجنة مترجم",
  "episode_number": 13,
  "title": "الحلقة 13",
  "date_added": "الأربعاء 17 ديسمبر 2025 - 02:33 صباحا",
  "last_updated": "2026-01-12T20:43:57.000529Z",
  "servers": {
    "watch": [
      {
        "name": "أكوام",
        "type": "akwam",
        "url": "https://ak.sv/episode/91663/اطفال-الجنة-مترجم/الحلقة-13",
        "quality": "720p",
        "source": "akwam"
      }
    ],
    "download": [
      {
        "name": "أكوام",
        "url": "https://ak.sv/episode/91663/اطفال-الجنة-مترجم/الحلقة-13",
        "quality": "720p",
        "size": "",
        "source": "akwam"
      }
    ]
  }
}