{
  "series_id": "5092",
  "series_title": "الحب الأفلاطوني مدبلج",
  "episode_number": 3,
  "title": "الحلقة 3",
  "date_added": "الجمعة 19 سبتمبر 2025 - 02:31 مساءاً",
  "last_updated": "2026-01-14T08:39:33.226526Z",
  "servers": {
    "watch": [
      {
        "name": "أكوام",
        "type": "akwam",
        "url": "https://ak.sv/episode/89369/الحب-الأفلاطوني-مدبلج/الحلقة-3",
        "quality": "720p",
        "source": "akwam"
      }
    ],
    "download": [
      {
        "name": "أكوام",
        "url": "https://ak.sv/episode/89369/الحب-الأفلاطوني-مدبلج/الحلقة-3",
        "quality": "720p",
        "size": "",
        "source": "akwam"
      }
    ]
  }
}