{
  "series_id": "5095",
  "series_title": "الخليفة",
  "episode_number": 2,
  "title": "الحلقة 2",
  "date_added": "الجمعة 26 سبتمبر 2025 - 12:28 مساءاً",
  "last_updated": "2026-01-13T00:48:50.573541Z",
  "servers": {
    "watch": [
      {
        "name": "أكوام",
        "type": "akwam",
        "url": "https://ak.sv/episode/89554/الخليفة/الحلقة-2",
        "quality": "720p",
        "source": "akwam"
      }
    ],
    "download": [
      {
        "name": "أكوام",
        "url": "https://ak.sv/episode/89554/الخليفة/الحلقة-2",
        "quality": "720p",
        "size": "",
        "source": "akwam"
      }
    ]
  }
}