{
  "series_id": "5095",
  "series_title": "الخليفة",
  "episode_number": 9,
  "title": "الحلقة 9",
  "date_added": "الجمعة 21 نوفمبر 2025 - 02:24 صباحا",
  "last_updated": "2026-01-13T00:48:50.573570Z",
  "servers": {
    "watch": [
      {
        "name": "أكوام",
        "type": "akwam",
        "url": "https://ak.sv/episode/90947/الخليفة/الحلقة-9",
        "quality": "720p",
        "source": "akwam"
      }
    ],
    "download": [
      {
        "name": "أكوام",
        "url": "https://ak.sv/episode/90947/الخليفة/الحلقة-9",
        "quality": "720p",
        "size": "",
        "source": "akwam"
      }
    ]
  }
}