{
  "series_id": "5103",
  "series_title": "حلم أشرف الموسم الثاني مدبلج",
  "episode_number": 12,
  "title": "الحلقة 12",
  "date_added": "الخميس 23 أكتوبر 2025 - 09:49 مساءاً",
  "last_updated": "2026-01-12T20:43:48.812187Z",
  "servers": {
    "watch": [
      {
        "name": "أكوام",
        "type": "akwam",
        "url": "https://ak.sv/episode/90173/حلم-أشرف-الموسم-الثاني-مدبلج/الحلقة-12",
        "quality": "720p",
        "source": "akwam"
      }
    ],
    "download": [
      {
        "name": "أكوام",
        "url": "https://ak.sv/episode/90173/حلم-أشرف-الموسم-الثاني-مدبلج/الحلقة-12",
        "quality": "720p",
        "size": "",
        "source": "akwam"
      }
    ]
  }
}