{
  "series_id": "5114",
  "series_title": "فخر السويدي",
  "episode_number": 4,
  "title": "الحلقة 4",
  "date_added": "الإثنين 06 أكتوبر 2025 - 07:23 مساءاً",
  "last_updated": "2026-01-12T20:44:36.288112Z",
  "servers": {
    "watch": [
      {
        "name": "أكوام",
        "type": "akwam",
        "url": "https://ak.sv/episode/89704/فخر-السويدي/الحلقة-4",
        "quality": "720p",
        "source": "akwam"
      }
    ],
    "download": [
      {
        "name": "أكوام",
        "url": "https://ak.sv/episode/89704/فخر-السويدي/الحلقة-4",
        "quality": "720p",
        "size": "",
        "source": "akwam"
      }
    ]
  }
}