{
  "series_id": "5115",
  "series_title": "جراح الروح",
  "episode_number": 96,
  "title": "الحلقة 96",
  "date_added": "الأربعاء 31 ديسمبر 2025 - 12:14 صباحا",
  "last_updated": "2026-01-14T08:38:14.119026Z",
  "servers": {
    "watch": [
      {
        "name": "أكوام",
        "type": "akwam",
        "url": "https://ak.sv/episode/92059/جراح-الروح/الحلقة-96",
        "quality": "720p",
        "source": "akwam"
      }
    ],
    "download": [
      {
        "name": "أكوام",
        "url": "https://ak.sv/episode/92059/جراح-الروح/الحلقة-96",
        "quality": "720p",
        "size": "",
        "source": "akwam"
      }
    ]
  }
}