{
  "series_id": "5115",
  "series_title": "جراح الروح",
  "episode_number": 91,
  "title": "الحلقة 91",
  "date_added": "الثلاثاء 30 ديسمبر 2025 - 01:50 صباحا",
  "last_updated": "2026-01-12T20:43:29.735697Z",
  "servers": {
    "watch": [
      {
        "name": "أكوام",
        "type": "akwam",
        "url": "https://ak.sv/episode/92023/جراح-الروح/الحلقة-91",
        "quality": "720p",
        "source": "akwam"
      }
    ],
    "download": [
      {
        "name": "أكوام",
        "url": "https://ak.sv/episode/92023/جراح-الروح/الحلقة-91",
        "quality": "720p",
        "size": "",
        "source": "akwam"
      }
    ]
  }
}