{
  "series_id": "5115",
  "series_title": "جراح الروح",
  "episode_number": 84,
  "title": "الحلقة 84",
  "date_added": "الخميس 25 ديسمبر 2025 - 11:15 مساءاً",
  "last_updated": "2026-01-14T08:38:14.118967Z",
  "servers": {
    "watch": [
      {
        "name": "أكوام",
        "type": "akwam",
        "url": "https://ak.sv/episode/91933/جراح-الروح/الحلقة-84",
        "quality": "720p",
        "source": "akwam"
      }
    ],
    "download": [
      {
        "name": "أكوام",
        "url": "https://ak.sv/episode/91933/جراح-الروح/الحلقة-84",
        "quality": "720p",
        "size": "",
        "source": "akwam"
      }
    ]
  }
}