{
  "series_id": "5116",
  "series_title": "حياة قلبي الجزء السابع",
  "episode_number": 66,
  "title": "الحلقة 66",
  "date_added": "الإثنين 22 ديسمبر 2025 - 01:25 صباحا",
  "last_updated": "2026-01-12T20:43:31.522837Z",
  "servers": {
    "watch": [
      {
        "name": "أكوام",
        "type": "akwam",
        "url": "https://ak.sv/episode/91793/حياة-قلبي-الجزء-السابع/الحلقة-66",
        "quality": "720p",
        "source": "akwam"
      }
    ],
    "download": [
      {
        "name": "أكوام",
        "url": "https://ak.sv/episode/91793/حياة-قلبي-الجزء-السابع/الحلقة-66",
        "quality": "720p",
        "size": "",
        "source": "akwam"
      }
    ]
  }
}