{
  "series_id": "5122",
  "series_title": "لينك",
  "episode_number": 8,
  "title": "الحلقة 8",
  "date_added": "الإثنين 20 أكتوبر 2025 - 09:56 مساءاً",
  "last_updated": "2026-01-12T20:44:20.739477Z",
  "servers": {
    "watch": [
      {
        "name": "أكوام",
        "type": "akwam",
        "url": "https://ak.sv/episode/90096/لينك/الحلقة-8",
        "quality": "720p",
        "source": "akwam"
      }
    ],
    "download": [
      {
        "name": "أكوام",
        "url": "https://ak.sv/episode/90096/لينك/الحلقة-8",
        "quality": "720p",
        "size": "",
        "source": "akwam"
      }
    ]
  }
}