{
  "series_id": "5142",
  "series_title": "خيوط الحياة مدبلج",
  "episode_number": 11,
  "title": "الحلقة 11",
  "date_added": "الأحد 16 نوفمبر 2025 - 07:17 مساءاً",
  "last_updated": "2026-01-13T06:15:55.691981Z",
  "servers": {
    "watch": [
      {
        "name": "أكوام",
        "type": "akwam",
        "url": "https://ak.sv/episode/90814/خيوط-الحياة-مدبلج/الحلقة-11",
        "quality": "720p",
        "source": "akwam"
      }
    ],
    "download": [
      {
        "name": "أكوام",
        "url": "https://ak.sv/episode/90814/خيوط-الحياة-مدبلج/الحلقة-11",
        "quality": "720p",
        "size": "",
        "source": "akwam"
      }
    ]
  }
}