{
  "series_id": "5142",
  "series_title": "خيوط الحياة مدبلج",
  "episode_number": 34,
  "title": "الحلقة 34",
  "date_added": "السبت 13 ديسمبر 2025 - 05:13 مساءاً",
  "last_updated": "2026-01-13T02:56:14.294032Z",
  "servers": {
    "watch": [
      {
        "name": "أكوام",
        "type": "akwam",
        "url": "https://ak.sv/episode/91513/خيوط-الحياة-مدبلج/الحلقة-34",
        "quality": "720p",
        "source": "akwam"
      }
    ],
    "download": [
      {
        "name": "أكوام",
        "url": "https://ak.sv/episode/91513/خيوط-الحياة-مدبلج/الحلقة-34",
        "quality": "720p",
        "size": "",
        "source": "akwam"
      }
    ]
  }
}