{
  "series_id": "5146",
  "series_title": "Talamasca: The Secret Order",
  "episode_number": 4,
  "title": "الحلقة 4",
  "date_added": "الأحد 09 نوفمبر 2025 - 11:57 مساءاً",
  "last_updated": "2026-01-12T20:44:18.760881Z",
  "servers": {
    "watch": [
      {
        "name": "أكوام",
        "type": "akwam",
        "url": "https://ak.sv/episode/90598/talamasca-the-secret-order/الحلقة-4",
        "quality": "720p",
        "source": "akwam"
      }
    ],
    "download": [
      {
        "name": "أكوام",
        "url": "https://ak.sv/episode/90598/talamasca-the-secret-order/الحلقة-4",
        "quality": "720p",
        "size": "",
        "source": "akwam"
      }
    ]
  }
}