{
  "series_id": "5152",
  "series_title": "المحتالون مدبلج",
  "episode_number": 29,
  "title": "الحلقة 29",
  "date_added": "الأربعاء 19 نوفمبر 2025 - 06:08 مساءاً",
  "last_updated": "2026-01-14T08:39:20.957057Z",
  "servers": {
    "watch": [
      {
        "name": "أكوام",
        "type": "akwam",
        "url": "https://ak.sv/episode/90912/المحتالون-مدبلج/الحلقة-29",
        "quality": "720p",
        "source": "akwam"
      }
    ],
    "download": [
      {
        "name": "أكوام",
        "url": "https://ak.sv/episode/90912/المحتالون-مدبلج/الحلقة-29",
        "quality": "720p",
        "size": "",
        "source": "akwam"
      }
    ]
  }
}