{
  "series_id": "5155",
  "series_title": "الحسناء والعاصي",
  "episode_number": 23,
  "title": "الحلقة 23",
  "date_added": "الأربعاء 10 ديسمبر 2025 - 01:58 صباحا",
  "last_updated": "2026-01-12T20:44:05.415120Z",
  "servers": {
    "watch": [
      {
        "name": "أكوام",
        "type": "akwam",
        "url": "https://ak.sv/episode/91417/الحسناء-والعاصي/الحلقة-23",
        "quality": "720p",
        "source": "akwam"
      }
    ],
    "download": [
      {
        "name": "أكوام",
        "url": "https://ak.sv/episode/91417/الحسناء-والعاصي/الحلقة-23",
        "quality": "720p",
        "size": "",
        "source": "akwam"
      }
    ]
  }
}