{
  "series_id": "5155",
  "series_title": "الحسناء والعاصي",
  "episode_number": 20,
  "title": "الحلقة 20",
  "date_added": "الخميس 04 ديسمبر 2025 - 10:22 مساءاً",
  "last_updated": "2026-01-12T20:44:05.415109Z",
  "servers": {
    "watch": [
      {
        "name": "أكوام",
        "type": "akwam",
        "url": "https://ak.sv/episode/91295/الحسناء-والعاصي/الحلقة-20",
        "quality": "720p",
        "source": "akwam"
      }
    ],
    "download": [
      {
        "name": "أكوام",
        "url": "https://ak.sv/episode/91295/الحسناء-والعاصي/الحلقة-20",
        "quality": "720p",
        "size": "",
        "source": "akwam"
      }
    ]
  }
}