{
  "series_id": "5171",
  "series_title": "الاعراف مترجم",
  "episode_number": 77,
  "title": "الحلقة 77",
  "date_added": "السبت 23 مايو 2026 - 03:48 مساءاً",
  "last_updated": "2026-05-23T13:02:37.129231Z",
  "servers": {
    "watch": [
      {
        "name": "أكوام",
        "type": "akwam",
        "url": "https://akwam.it/episode/101055/الاعراف-مترجم/الحلقة-77",
        "quality": "720p",
        "source": "akwam"
      }
    ],
    "download": [
      {
        "name": "أكوام",
        "url": "https://akwam.it/episode/101055/الاعراف-مترجم/الحلقة-77",
        "quality": "720p",
        "size": "",
        "source": "akwam"
      }
    ]
  }
}