{
  "series_id": "5177",
  "series_title": "المنظمة مدبلج",
  "episode_number": 53,
  "title": "الحلقة 53",
  "date_added": "الأحد 11 يناير 2026 - 10:18 مساءاً",
  "last_updated": "2026-01-13T03:46:54.514249Z",
  "servers": {
    "watch": [
      {
        "name": "أكوام",
        "type": "akwam",
        "url": "https://ak.sv/episode/92359/المنظمة-مدبلج/الحلقة-53",
        "quality": "720p",
        "source": "akwam"
      }
    ],
    "download": [
      {
        "name": "أكوام",
        "url": "https://ak.sv/episode/92359/المنظمة-مدبلج/الحلقة-53",
        "quality": "720p",
        "size": "",
        "source": "akwam"
      }
    ]
  }
}