{
  "series_id": "5180",
  "series_title": "Spartacus: House of Ashur",
  "episode_number": 2,
  "title": "الحلقة 2",
  "date_added": "السبت 06 ديسمبر 2025 - 07:14 مساءاً",
  "last_updated": "2026-01-12T20:43:41.161560Z",
  "servers": {
    "watch": [
      {
        "name": "أكوام",
        "type": "akwam",
        "url": "https://ak.sv/episode/91320/spartacus-house-of-ashur/الحلقة-2",
        "quality": "720p",
        "source": "akwam"
      }
    ],
    "download": [
      {
        "name": "أكوام",
        "url": "https://ak.sv/episode/91320/spartacus-house-of-ashur/الحلقة-2",
        "quality": "720p",
        "size": "",
        "source": "akwam"
      }
    ]
  }
}