{
  "series_id": "5198",
  "series_title": "سجين الإيهام",
  "episode_number": 1,
  "title": "الحلقة 1",
  "date_added": "الثلاثاء 23 ديسمبر 2025 - 12:08 صباحا",
  "last_updated": "2026-01-12T20:43:35.651589Z",
  "servers": {
    "watch": [
      {
        "name": "أكوام",
        "type": "akwam",
        "url": "https://ak.sv/episode/91810/سجين-الإيهام/الحلقة-1",
        "quality": "720p",
        "source": "akwam"
      }
    ],
    "download": [
      {
        "name": "أكوام",
        "url": "https://ak.sv/episode/91810/سجين-الإيهام/الحلقة-1",
        "quality": "720p",
        "size": "",
        "source": "akwam"
      }
    ]
  }
}