{
  "series_id": "5207",
  "series_title": "ورود وذنوب مدبلج",
  "episode_number": 29,
  "title": "الحلقة 29",
  "date_added": "الثلاثاء 03 فبراير 2026 - 12:52 صباحا",
  "last_updated": "2026-02-03T01:04:59.434821Z",
  "servers": {
    "watch": [
      {
        "name": "أكوام",
        "type": "akwam",
        "url": "https://ak.sv/episode/93208/ورود-وذنوب-مدبلج/الحلقة-29",
        "quality": "720p",
        "source": "akwam"
      }
    ],
    "download": [
      {
        "name": "أكوام",
        "url": "https://ak.sv/episode/93208/ورود-وذنوب-مدبلج/الحلقة-29",
        "quality": "720p",
        "size": "",
        "source": "akwam"
      }
    ]
  }
}