{
  "series_id": "572",
  "series_title": "الرجل الخطأ",
  "episode_number": 17,
  "title": "الحلقة 17",
  "date_added": "السبت 15 اغسطس 2020 - 04:48 صباحا",
  "last_updated": "2026-01-14T08:44:06.014156Z",
  "servers": {
    "watch": [
      {
        "name": "أكوام",
        "type": "akwam",
        "url": "https://ak.sv/episode/13425/الرجل-الخطأ/الحلقة-17",
        "quality": "720p",
        "source": "akwam"
      }
    ],
    "download": [
      {
        "name": "أكوام",
        "url": "https://ak.sv/episode/13425/الرجل-الخطأ/الحلقة-17",
        "quality": "720p",
        "size": "",
        "source": "akwam"
      }
    ]
  }
}