{
  "series_id": "649",
  "series_title": "Sen Çal Kapimi",
  "episode_number": 30,
  "title": "الحلقة 30",
  "date_added": "الأحد 07 فبراير 2021 - 05:30 صباحا",
  "last_updated": "2026-01-13T06:18:02.773322Z",
  "servers": {
    "watch": [
      {
        "name": "أكوام",
        "type": "akwam",
        "url": "https://ak.sv/episode/23774/sen-çal-kapimi/الحلقة-30",
        "quality": "720p",
        "source": "akwam"
      }
    ],
    "download": [
      {
        "name": "أكوام",
        "url": "https://ak.sv/episode/23774/sen-çal-kapimi/الحلقة-30",
        "quality": "720p",
        "size": "",
        "source": "akwam"
      }
    ]
  }
}