{
  "series_id": "964",
  "series_title": "Emanet الموسم الاول",
  "episode_number": 137,
  "title": "الحلقة 137",
  "date_added": "الخميس 18 مارس 2021 - 11:54 مساءاً",
  "last_updated": "2026-01-13T02:57:59.097628Z",
  "servers": {
    "watch": [
      {
        "name": "أكوام",
        "type": "akwam",
        "url": "https://ak.sv/episode/26440/emanet-الموسم-الاول/الحلقة-137",
        "quality": "720p",
        "source": "akwam"
      }
    ],
    "download": [
      {
        "name": "أكوام",
        "url": "https://ak.sv/episode/26440/emanet-الموسم-الاول/الحلقة-137",
        "quality": "720p",
        "size": "",
        "source": "akwam"
      }
    ]
  }
}